musan/__init__.py
musan/load.py
musan/model.py
musan/predict.py
musan/utils.py
musan-0.0.3.dist-info/licenses/LICENSE
musan-0.0.3.dist-info/METADATA
musan-0.0.3.dist-info/WHEEL
musan-0.0.3.dist-info/top_level.txt
musan-0.0.3.dist-info/RECORD
