Metadata-Version: 2.4
Name: musan
Version: 0.0.3
Summary: This is the module for work with mel-specs based music analitycs models
Author-email: nikarpoff <nik.karpov103@mail.ru>
License:                                  Apache License
Project-URL: Repository, https://github.com/nikarpoff
Project-URL: Bug Tracker, https://github.com/yourusername/your-repo/issues
Keywords: transformers,music,analitycs,hugging_face
Classifier: License :: OSI Approved :: Apache Software License
Classifier: Programming Language :: Python :: 3
Classifier: Programming Language :: Python :: 3.8
Classifier: Programming Language :: Python :: 3.9
Classifier: Programming Language :: Python :: 3.10
Classifier: Programming Language :: Python :: 3.11
Classifier: Programming Language :: Python :: 3.12
License-File: LICENSE
Requires-Dist: torch==2.7.0
Requires-Dist: torchvision==0.22.0
Requires-Dist: torchaudio==2.7.0
Requires-Dist: huggingface_hub>=0.35.0
Dynamic: license-file
